pyprover/__coconut__.py
pyprover/__init__.py
pyprover/atoms.py
pyprover/constants.py
pyprover/logic.py
pyprover/parser.py
pyprover/tests.py
pyprover/tools.py
pyprover/util.py
pyprover-0.6.2.dist-info/LICENSE.txt
pyprover-0.6.2.dist-info/METADATA
pyprover-0.6.2.dist-info/WHEEL
pyprover-0.6.2.dist-info/top_level.txt
pyprover-0.6.2.dist-info/RECORD
